be/__init__.py
be/audit_logger.py
be/auto_register.py
be/autonomy_controller.py
be/conversation_manager.py
be/dt_core.py
be/dt_identity.py
be/dt_state.py
be/execution_node.py
be/rate_limiter.py
be/api/__init__.py
be/api/act.py
be/api/capabilities.py
be/api/chat.py
be/api/conversations.py
be/api/health.py
be/api/identities.py
be/api/security.py
be/api/state.py
be/api/stream.py
be/api/think.py
app.json
avyas_aurica_base_apps_digital_twin-3.8.0.dist-info/METADATA
avyas_aurica_base_apps_digital_twin-3.8.0.dist-info/WHEEL
avyas_aurica_base_apps_digital_twin-3.8.0.dist-info/RECORD
