Metadata-Version: 2.4
Name: avyas-aurica-base-apps-digital-twin
Version: 3.8.0
Summary: Aurica app: digital-twin
Requires-Python: >=3.11
Requires-Dist: fastapi>=0.104.0
Requires-Dist: uvicorn>=0.24.0
